robotics/__init__.py
robotics-1.0.3.dist-info/METADATA
robotics-1.0.3.dist-info/WHEEL
robotics-1.0.3.dist-info/top_level.txt
robotics-1.0.3.dist-info/RECORD
