Metadata-Version: 2.1
Name: robotics
Version: 1.0.3
Summary: package for robot kinematics analysis
Home-page: https://github.com/ryanGT/robotics
Author: Ryan Krauss
Author-email: ryanwkrauss@gmail.com
License: UNKNOWN
Platform: UNKNOWN
Classifier: Programming Language :: Python :: 3
Classifier: License :: OSI Approved :: MIT License
Classifier: Operating System :: OS Independent
